autogen_graph/__init__.py
autogen_graph/_digraph_group_chat.py
autogen_graph/_graph_builder.py
autogen_graph/_message_filter_agent.py
autogen_graph-0.1.2.dist-info/licenses/LICENSE.md
autogen_graph-0.1.2.dist-info/METADATA
autogen_graph-0.1.2.dist-info/WHEEL
autogen_graph-0.1.2.dist-info/top_level.txt
autogen_graph-0.1.2.dist-info/RECORD
