Metadata-Version: 2.4
Name: autogen-graph
Version: 0.1.2
Summary: Graph based execution for Autogen agentchat agents
Author-email: A Somaraju <abhinav@aegis-enterprise.com>
License: MIT
Project-URL: Repository, https://github.com/abhinav-aegis/autogen-graph
Project-URL: Issues, https://github.com/abhinav-aegis/autogen-graph/issues
Requires-Python: >=3.12
License-File: LICENSE.md
Requires-Dist: autogen-agentchat>=0.5.1
Dynamic: license-file
